npstructures/__init__.py
npstructures/arrayfunctions.py
npstructures/bitarray.py
npstructures/hashtable.py
npstructures/mixin.py
npstructures/npdataclasses.py
npstructures/raggedshape.py
npstructures/runlengtharray.py
npstructures/testing.py
npstructures/util.py
npstructures/raggedarray/__init__.py
npstructures/raggedarray/base.py
npstructures/raggedarray/indexablearray.py
npstructures/raggedarray/raggedslice.py
npstructures-0.2.19.dist-info/AUTHORS.rst
npstructures-0.2.19.dist-info/LICENSE
npstructures-0.2.19.dist-info/METADATA
npstructures-0.2.19.dist-info/WHEEL
npstructures-0.2.19.dist-info/top_level.txt
npstructures-0.2.19.dist-info/RECORD
