Metadata-Version: 2.1
Name: npstructures
Version: 0.2.19
Summary: Simple data structures that augments the numpy library
Home-page: https://github.com/knutdrand/npstructures
Author: Knut Rand
Author-email: knutdrand@gmail.com
License: MIT license
Keywords: npstructures
Classifier: Development Status :: 2 - Pre-Alpha
Classifier: Intended Audience :: Developers
Classifier: License :: OSI Approved :: MIT License
Classifier: Natural Language :: English
Classifier: Programming Language :: Python :: 3
Classifier: Programming Language :: Python :: 3.6
Classifier: Programming Language :: Python :: 3.7
Classifier: Programming Language :: Python :: 3.8
Requires-Python: >=3.6
License-File: LICENSE
License-File: AUTHORS.rst
Requires-Dist: numpy >=1.19
